anchor_txt
