Metadata-Version: 1.2
Name: anchor-txt
Version: 0.1.5
Summary: attributes in markdown
Home-page: https://github.com/vitiral/anchor_txt
Author: Rett Berg
Author-email: googberg@gmail.com
License: MIT or APACHE-2.0
Project-URL: Documentation, https://anchor_txt.readthedocs.io/
Project-URL: Changelog, https://anchor_txt.readthedocs.io/en/latest/changelog.html
Project-URL: Issue Tracker, https://github.com/vitiral/anchor_txt/issues
Platform: UNKNOWN
Classifier: Development Status :: 5 - Production/Stable
Classifier: Intended Audience :: Developers
Classifier: License :: OSI Approved :: MIT License
Classifier: Operating System :: Unix
Classifier: Operating System :: POSIX
Classifier: Operating System :: Microsoft :: Windows
Classifier: Programming Language :: Python
Classifier: Programming Language :: Python :: 2.7
Classifier: Programming Language :: Python :: 3
Classifier: Programming Language :: Python :: 3.4
Classifier: Programming Language :: Python :: 3.5
Classifier: Programming Language :: Python :: 3.6
Classifier: Programming Language :: Python :: 3.7
Classifier: Programming Language :: Python :: Implementation :: CPython
Classifier: Programming Language :: Python :: Implementation :: PyPy
Classifier: Topic :: Utilities
Requires-Python: >=2.7
